blinky.v
module blinky #(parameter CLK_HZ = 12_000_000) (
    input  wire       CLOCK_12,         // board clock
    input  wire [3:0] SW,          // switches SW0–SW3
    output wire [3:0] LEDG,   // green LEDs copy the switches
    output reg        LEDR      // red LED blinks once a second
);
    reg [31:0] count = 0;

    always @(posedge CLOCK_12) begin            // on every clock tick...
        if (count == CLK_HZ/2 - 1) begin   // ...after half a second's worth of ticks
            count   <= 0;
            LEDR <= ~LEDR;           // flip the LED
        end else begin
            count   <= count + 1;
        end
    end

    assign LEDG = SW;                 // plain wires, no clock involved
    initial LEDR = 0;
endmodule

blinky_tb.v
// blinky_tb.v - testbench: a fake "board" that runs blinky in simulation
`timescale 1ns/1ns
module blinky_tb;
    reg        clk = 0;
    reg  [3:0] sw  = 4'b0000;
    wire [3:0] led_green;
    wire       led_red;

    // Pretend the clock is 10 Hz so the LED toggles every 5 ticks
    // (instead of waiting 6 million ticks).
    blinky #(.CLK_HZ(10)) dut (.CLOCK_12(clk), .SW(sw), .LEDG(led_green), .LEDR(led_red));

    always #5 clk = ~clk;                  // a tick every 10 ns

    initial begin
        $dumpfile("blinky.vcd");           // waveform file you can view
        $dumpvars(0, blinky_tb);
        $monitor("t=%0t  sw=%b  green=%b  red=%b", $time, sw, led_green, led_red);
        #120 sw = 4'b1010;                 // flip some switches
        #120 sw = 4'b0110;
        #120 $finish;
    end
endmodule

blinky.vcd
$date
	Sat Oct  3 21:01:23 2026
$end
$version
	Icarus Verilog
$end
$timescale
	1ns
$end
$scope module blinky_tb $end
$var wire 1 ! led_red $end
$var wire 4 " led_green [3:0] $end
$var reg 1 # clk $end
$var reg 4 $ sw [3:0] $end
$scope module dut $end
$var wire 1 # CLOCK_12 $end
$var wire 4 % LEDG [3:0] $end
$var wire 4 & SW [3:0] $end
$var parameter 32 ' CLK_HZ $end
$var reg 1 ! LEDR $end
$var reg 32 ( count [31:0] $end
$upscope $end
$upscope $end
$enddefinitions $end
$comment Show the parameter values. $end
$dumpall
b1010 '
$end
#0
$dumpvars
b0 (
b0 &
b0 %
b0 $
0#
b0 "
0!
$end
#5
b1 (
1#
#10
0#
#15
b10 (
1#
#20
0#
#25
b11 (
1#
#30
0#
#35
b100 (
1#
#40
0#
#45
1!
b0 (
1#
#50
0#
#55
b1 (
1#
#60
0#
#65
b10 (
1#
#70
0#
#75
b11 (
1#
#80
0#
#85
b100 (
1#
#90
0#
#95
0!
b0 (
1#
#100
0#
#105
b1 (
1#
#110
0#
#115
b10 (
1#
#120
0#
b1010 "
b1010 %
b1010 $
b1010 &
#125
b11 (
1#
#130
0#
#135
b100 (
1#
#140
0#
#145
1!
b0 (
1#
#150
0#
#155
b1 (
1#
#160
0#
#165
b10 (
1#
#170
0#
#175
b11 (
1#
#180
0#
#185
b100 (
1#
#190
0#
#195
0!
b0 (
1#
#200
0#
#205
b1 (
1#
#210
0#
#215
b10 (
1#
#220
0#
#225
b11 (
1#
#230
0#
#235
b100 (
1#
#240
0#
b110 "
b110 %
b110 $
b110 &
#245
1!
b0 (
1#
#250
0#
#255
b1 (
1#
#260
0#
#265
b10 (
1#
#270
0#
#275
b11 (
1#
#280
0#
#285
b100 (
1#
#290
0#
#295
0!
b0 (
1#
#300
0#
#305
b1 (
1#
#310
0#
#315
b10 (
1#
#320
0#
#325
b11 (
1#
#330
0#
#335
b100 (
1#
#340
0#
#345
1!
b0 (
1#
#350
0#
#355
b1 (
1#
